django_spreadsheets/__init__.py
django_spreadsheets/admin.py
django_spreadsheets/apps.py
django_spreadsheets/autodiscover.py
django_spreadsheets/base_config.py
django_spreadsheets/conf/__init__.py
django_spreadsheets/conf/settings.py
django_spreadsheets/constants.py
django_spreadsheets/errors.py
django_spreadsheets/exceptions.py
django_spreadsheets/exporter.py
django_spreadsheets/forms.py
django_spreadsheets/importer.py
django_spreadsheets/locale/fr/LC_MESSAGES/django.mo
django_spreadsheets/locale/fr/LC_MESSAGES/django.po
django_spreadsheets/registry.py
django_spreadsheets/shortcuts.py
django_spreadsheets/templates/spreadsheets/base.html
django_spreadsheets/templates/spreadsheets/done.html
django_spreadsheets/templates/spreadsheets/export_index.html
django_spreadsheets/templates/spreadsheets/import_index.html
django_spreadsheets/templates/spreadsheets/wizard.html
django_spreadsheets/urls.py
django_spreadsheets/validation.py
django_spreadsheets/views.py
django_spreadsheets-1.4.4.dist-info/LICENSE
django_spreadsheets-1.4.4.dist-info/METADATA
django_spreadsheets-1.4.4.dist-info/WHEEL
django_spreadsheets-1.4.4.dist-info/RECORD
