Metadata-Version: 2.3
Name: django_spreadsheets
Version: 1.4.4
Summary: Import from and export to XLSX files with data validation.
License: BSD-3-Clause
Author: Kapt dev team
Author-email: dev@kapt.mobi
Requires-Python: >=3.8,<4.0
Classifier: License :: OSI Approved :: BSD License
Classifier: Programming Language :: Python :: 3
Classifier: Programming Language :: Python :: 3.8
Classifier: Programming Language :: Python :: 3.9
Classifier: Programming Language :: Python :: 3.10
Classifier: Programming Language :: Python :: 3.11
Classifier: Programming Language :: Python :: 3.12
Classifier: Programming Language :: Python :: 3.13
Requires-Dist: Django (>=3.0,<5)
Requires-Dist: django-formtools (>=2.5.1,<3.0.0)
Requires-Dist: openpyxl (>=3.1.5,<4.0.0)
Project-URL: Repository, https://gitlab.com/kapt/open-source/django-spreadsheets
